ActivityTasks/Activity_Module.py
ActivityTasks/MultiTask_module.py
ActivityTasks/Queue_Module.py
ActivityTasks/Task_Module.py
ActivityTasks/__init__.py
activityTasks_udacity_inventrohyder-0.1.0a0.dist-info/METADATA
activityTasks_udacity_inventrohyder-0.1.0a0.dist-info/WHEEL
activityTasks_udacity_inventrohyder-0.1.0a0.dist-info/top_level.txt
activityTasks_udacity_inventrohyder-0.1.0a0.dist-info/RECORD
