Metadata-Version: 2.1
Name: activityTasks-udacity-inventrohyder
Version: 0.1.0a0
Summary: A Activity and Tasks package
Home-page: https://github.com/Inventrohyder/CS110/tree/master/Assignments/cs110_assignment_2/package
Author: Haitham Alhad
Author-email: haitham.hyder@minerva.kgi.edu
License: UNKNOWN
Platform: UNKNOWN
